drone_approval/__init__.py
drone_approval/api.py
drone_approval/cli.py
drone_approval/config.py
drone_approval/models.py
drone_approval/schemas.py
drone_approval-0.1.5.dist-info/entry_points.txt
drone_approval-0.1.5.dist-info/LICENSE
drone_approval-0.1.5.dist-info/WHEEL
drone_approval-0.1.5.dist-info/METADATA
drone_approval-0.1.5.dist-info/RECORD
