Metadata-Version: 2.1
Name: drone-approval
Version: 0.1.5
Summary: 
Author: Martin Ortbauer
Author-email: mortbauer@gmail.com
Requires-Python: >=3.7,<4.0
Classifier: Programming Language :: Python :: 3
Classifier: Programming Language :: Python :: 3.10
Classifier: Programming Language :: Python :: 3.7
Classifier: Programming Language :: Python :: 3.8
Classifier: Programming Language :: Python :: 3.9
Provides-Extra: server
Requires-Dist: aerich (>=0.6.3,<0.7.0); extra == "server"
Requires-Dist: aiosmtplib (>=1.1.6,<2.0.0); extra == "server"
Requires-Dist: click (>=8.1.3,<9.0.0)
Requires-Dist: coloredlogs (>=15.0.1,<16.0.0); extra == "server"
Requires-Dist: fastapi (>=0.76.0,<0.77.0); extra == "server"
Requires-Dist: httpx (>=0.22.0,<0.23.0)
Requires-Dist: pydantic[dotenv] (>=1.9.0,<2.0.0)
Requires-Dist: tortoise-orm (>=0.19.0,<0.20.0); extra == "server"
Requires-Dist: uvicorn (>=0.17.6,<0.18.0); extra == "server"
